frostfs_testlib/__init__.py
frostfs_testlib/defaults.py
frostfs_testlib/analytics/__init__.py
frostfs_testlib/analytics/test_case.py
frostfs_testlib/analytics/test_collector.py
frostfs_testlib/analytics/test_exporter.py
frostfs_testlib/analytics/testrail_exporter.py
frostfs_testlib/blockchain/__init__.py
frostfs_testlib/blockchain/multisig.py
frostfs_testlib/blockchain/role_designation.py
frostfs_testlib/blockchain/rpc_client.py
frostfs_testlib/cli/__init__.py
frostfs_testlib/cli/cli_command.py
frostfs_testlib/cli/frostfs_adm/__init__.py
frostfs_testlib/cli/frostfs_adm/adm.py
frostfs_testlib/cli/frostfs_adm/config.py
frostfs_testlib/cli/frostfs_adm/morph.py
frostfs_testlib/cli/frostfs_adm/storage_config.py
frostfs_testlib/cli/frostfs_adm/subnet.py
frostfs_testlib/cli/frostfs_adm/version.py
frostfs_testlib/cli/frostfs_authmate/__init__.py
frostfs_testlib/cli/frostfs_authmate/authmate.py
frostfs_testlib/cli/frostfs_authmate/secret.py
frostfs_testlib/cli/frostfs_authmate/version.py
frostfs_testlib/cli/frostfs_cli/__init__.py
frostfs_testlib/cli/frostfs_cli/accounting.py
frostfs_testlib/cli/frostfs_cli/acl.py
frostfs_testlib/cli/frostfs_cli/cli.py
frostfs_testlib/cli/frostfs_cli/container.py
frostfs_testlib/cli/frostfs_cli/netmap.py
frostfs_testlib/cli/frostfs_cli/object.py
frostfs_testlib/cli/frostfs_cli/session.py
frostfs_testlib/cli/frostfs_cli/shards.py
frostfs_testlib/cli/frostfs_cli/storagegroup.py
frostfs_testlib/cli/frostfs_cli/util.py
frostfs_testlib/cli/frostfs_cli/version.py
frostfs_testlib/cli/neogo/__init__.py
frostfs_testlib/cli/neogo/candidate.py
frostfs_testlib/cli/neogo/contract.py
frostfs_testlib/cli/neogo/db.py
frostfs_testlib/cli/neogo/go.py
frostfs_testlib/cli/neogo/nep17.py
frostfs_testlib/cli/neogo/network_type.py
frostfs_testlib/cli/neogo/node.py
frostfs_testlib/cli/neogo/query.py
frostfs_testlib/cli/neogo/version.py
frostfs_testlib/cli/neogo/wallet.py
frostfs_testlib/hosting/__init__.py
frostfs_testlib/hosting/config.py
frostfs_testlib-1.3.0.dist-info/LICENSE
frostfs_testlib-1.3.0.dist-info/METADATA
frostfs_testlib-1.3.0.dist-info/WHEEL
frostfs_testlib-1.3.0.dist-info/entry_points.txt
frostfs_testlib-1.3.0.dist-info/top_level.txt
frostfs_testlib-1.3.0.dist-info/RECORD
