Metadata-Version: 2.1
Name: frostfs-testlib
Version: 1.3.0
Summary: Building blocks and utilities to facilitate development of automated tests for FrostFS system
Author-email: NSPCC <info@nspcc.ru>
License: GNU General Public License v3 (GPLv3)
Project-URL: Homepage, https://github.com/TrueCloudLab/frostfs-testlib
Keywords: frostfs,test
Classifier: License :: OSI Approved :: GNU General Public License v3 (GPLv3)
Classifier: Programming Language :: Python
Classifier: Programming Language :: Python :: 3
Requires-Python: >=3.10
License-File: LICENSE
Requires-Dist: allure-python-commons (>=2.9.45)
Requires-Dist: docker (>=4.4.0)
Requires-Dist: neo-mamba (==1.0.0)
Requires-Dist: paramiko (>=2.10.3)
Requires-Dist: pexpect (>=4.8.0)
Requires-Dist: requests (>=2.28.0)
Requires-Dist: docstring-parser (>=0.15)
Requires-Dist: testrail-api (>=1.12.0)
Requires-Dist: importlib-metadata (>=5.0) ; python_version < "3.10"
Provides-Extra: dev
Requires-Dist: black ; extra == 'dev'
Requires-Dist: bumpver ; extra == 'dev'
Requires-Dist: isort ; extra == 'dev'
Requires-Dist: pre-commit ; extra == 'dev'
